lambda_dd_metrics.py
setup.py
lambda_dd_metrics.egg-info/PKG-INFO
lambda_dd_metrics.egg-info/SOURCES.txt
lambda_dd_metrics.egg-info/dependency_links.txt
lambda_dd_metrics.egg-info/top_level.txt
lambda_dd_metrics.egg-info/zip-safe